<debate xmlns:tei="http://www.tei-c.org/ns/1.0">
  <date>2021-01-19</date>
  <chamber>House of Commons</chamber>
  <speaker>
    <id>#ScottBenton</id>
    <name>Scott Benton</name>
    <sex>M</sex>
    <parliament>House of Commons</parliament>
    <party>Conservative</party>
    <contributions>2</contributions>
  </speaker>
  <speaker>
    <id>#AlisonThewliss</id>
    <name>Alison Thewliss</name>
    <sex>F</sex>
    <parliament>House of Commons</parliament>
    <party>Scottish National Party</party>
    <contributions>2</contributions>
  </speaker>
  <speaker>
    <id>#RebeccaLongBailey</id>
    <name>Rebecca Long-Bailey</name>
    <sex>F</sex>
    <parliament>House of Commons</parliament>
    <party>Labour</party>
    <contributions>2</contributions>
  </speaker>
  <speaker>
    <id>#JamesCleverly</id>
    <name>James Cleverly</name>
    <sex>M</sex>
    <parliament>House of Commons</parliament>
    <party>Conservative</party>
    <contributions>5</contributions>
  </speaker>
  <speaker>
    <id>#WayneDavid</id>
    <name>Wayne David</name>
    <sex>M</sex>
    <parliament>House of Commons</parliament>
    <party>Labour</party>
    <contributions>1</contributions>
  </speaker>
</debate>
